brainload/__init__.py
brainload/annotations.py
brainload/braindescriptors.py
brainload/brainlocate.py
brainload/brainvoxlocate.py
brainload/brainwrite.py
brainload/freesurferdata.py
brainload/freesurferview.py
brainload/meshexport.py
brainload/nitools.py
brainload/qa.py
brainload/spatial.py
brainload/spatial_transform.py
brainload/stats.py
brainload/surfacegraph.py
brainload/clients/__init__.py
brainload/clients/brain_consistency.py
brainload/clients/brain_fs_space_info.py
brainload/clients/brain_mesh_info.py
brainload/clients/brain_morph_info.py
brainload/clients/brain_vol_info.py
brainload/clients/intersurface.py
brainload/clients/visualize_verts.py
brainload-0.3.5.dist-info/LICENSE
brainload-0.3.5.dist-info/METADATA
brainload-0.3.5.dist-info/WHEEL
brainload-0.3.5.dist-info/entry_points.txt
brainload-0.3.5.dist-info/top_level.txt
brainload-0.3.5.dist-info/RECORD
