Metadata-Version: 2.1
Name: brainload
Version: 0.3.5
Summary: Load FreeSurfer brain imaging data with minimal cognitive load.
Home-page: https://github.com/dfsp-spirit/brainload
Author: Tim Schäfer
Author-email: ts+code@rcmd.org
License: MIT
Keywords: neuroimaging freesurfer nibabel load mgh curv MRI morphometry
Platform: UNKNOWN
Classifier: Development Status :: 3 - Alpha
Classifier: Intended Audience :: Developers
Classifier: Intended Audience :: Science/Research
Classifier: License :: OSI Approved :: MIT License
Classifier: Programming Language :: Python :: 3
Classifier: Programming Language :: Python :: 3.5
Classifier: Programming Language :: Python :: 3.6
Classifier: Programming Language :: Python :: 3.7
Requires-Dist: numpy
Requires-Dist: nibabel
